{"cameraMode":{"drawMode":0,"name":"Shaded","section":"Shading Mode"},"sceneLighting":true,"audioPlay":false,"sceneViewState":{"m_AlwaysRefresh":false,"showFog":true,"showSkybox":true,"showFlares":true,"showImageEffects":true,"showParticleSystems":true,"showVisualEffectGraphs":true,"m_FxEnabled":true},"in2DMode":false,"pivot":{"x":-6.336097240447998,"y":3.137187957763672,"z":-1.1776123046875},"rotation":{"x":-0.21433788537979127,"y":-0.05067038908600807,"z":0.011134631000459195,"w":-0.9753812551498413},"size":10.0,"orthographic":false}